src/veracode-firewall-demo/__init__.py
veracode_firewall_demo-0.1.0.dist-info/METADATA
veracode_firewall_demo-0.1.0.dist-info/WHEEL
veracode_firewall_demo-0.1.0.dist-info/RECORD
